tm352_app/__about__.py
tm352_app/__init__.py
tm352_app/__main__.py
tm352_app/block2.py
tm352_app/cli.py
tm352_app/ema.py
tm352_app/tma01.py
tm352_app/tma02.py
tm352_app/vce.py
tm352_app-24.3.3.dist-info/METADATA
tm352_app-24.3.3.dist-info/WHEEL
tm352_app-24.3.3.dist-info/entry_points.txt
tm352_app-24.3.3.dist-info/licenses/LICENSE.txt
tm352_app-24.3.3.dist-info/RECORD
