Metadata-Version: 2.4
Name: tm352-app
Version: 24.3.3
Project-URL: Documentation, https://github.com/Mark Hall/tm352-app#readme
Project-URL: Issues, https://github.com/Mark Hall/tm352-app/issues
Project-URL: Source, https://github.com/Mark Hall/tm352-app
Author-email: Mark Hall <mark.hall@work.room3b.eu>
License-Expression: MIT
License-File: LICENSE.txt
Classifier: Development Status :: 4 - Beta
Classifier: Programming Language :: Python
Classifier: Programming Language :: Python :: 3.11
Classifier: Programming Language :: Python :: 3.12
Classifier: Programming Language :: Python :: Implementation :: CPython
Classifier: Programming Language :: Python :: Implementation :: PyPy
Requires-Python: >=3.11
Requires-Dist: psutil<7,>=6.0.0
Requires-Dist: typer
